langchain_opengradient/__init__.py
langchain_opengradient/toolkits.py
langchain_opengradient-0.1.2.dist-info/LICENSE
langchain_opengradient-0.1.2.dist-info/METADATA
langchain_opengradient-0.1.2.dist-info/WHEEL
langchain_opengradient-0.1.2.dist-info/RECORD
