Metadata-Version: 2.3
Name: langchain-opengradient
Version: 0.1.2
Summary: An integration package connecting OpenGradient and LangChain
License: MIT
Requires-Python: >=3.9,<4.0
Classifier: License :: OSI Approved :: MIT License
Classifier: Programming Language :: Python :: 3
Classifier: Programming Language :: Python :: 3.9
Classifier: Programming Language :: Python :: 3.10
Classifier: Programming Language :: Python :: 3.11
Classifier: Programming Language :: Python :: 3.12
Classifier: Programming Language :: Python :: 3.13
Requires-Dist: langchain-core (>=0.3.15,<0.4.0)
Requires-Dist: opengradient (>=0.4.7,<0.5.0) ; python_version >= "3.10" and python_version < "4.0"
Requires-Dist: pydantic (>=2.10.6,<3.0.0)
Project-URL: Repository, https://github.com/langchain-ai/langchain
Project-URL: Release Notes, https://github.com/langchain-ai/langchain/releases?q=tag%3A%22opengradient%3D%3D0%22&expanded=true
Project-URL: Source Code, https://github.com/langchain-ai/langchain/tree/master/libs/partners/opengradient
